{
  "records": [
    {
      "symbol": "SKLUSDT",
      "date": "2026-07-10",
      "pct": 48.91041162227603,
      "open": "0.0041300",
      "high": "0.0061500",
      "close": "0.0048720"
    },
    {
      "symbol": "TUSDT",
      "date": "2026-07-11",
      "pct": 42.66081871345029,
      "open": "0.0034200",
      "high": "0.0048790",
      "close": "0.0046400"
    },
    {
      "symbol": "THEUSDT",
      "date": "2026-07-09",
      "pct": 29.946524064171136,
      "open": "0.052360",
      "high": "0.068040",
      "close": "0.059180"
    },
    {
      "symbol": "DEXEUSDT",
      "date": "2026-07-10",
      "pct": 31.447883315546083,
      "open": "28.1100",
      "high": "36.9500",
      "close": "35.0300"
    },
    {
      "symbol": "SXTUSDT",
      "date": "2026-07-11",
      "pct": 49.06814625124484,
      "open": "0.0070290",
      "high": "0.010478",
      "close": "0.0093650"
    },
    {
      "symbol": "SKYAIUSDT",
      "date": "2026-07-09",
      "pct": 51.64359861591694,
      "open": "0.034680",
      "high": "0.052590",
      "close": "0.038050"
    },
    {
      "symbol": "BUSDT",
      "date": "2026-07-10",
      "pct": 47.86967418546366,
      "open": "0.15960",
      "high": "0.23600",
      "close": "0.22510"
    },
    {
      "symbol": "AINUSDT",
      "date": "2026-07-09",
      "pct": 27.562893081760986,
      "open": "0.063600",
      "high": "0.081130",
      "close": "0.079460"
    },
    {
      "symbol": "VELVETUSDT",
      "date": "2026-07-10",
      "pct": 52.33354075917861,
      "open": "0.48210",
      "high": "0.73440",
      "close": "0.47380"
    },
    {
      "symbol": "TACUSDT",
      "date": "2026-07-09",
      "pct": 85.74569439355074,
      "open": "0.0027290",
      "high": "0.0050690",
      "close": "0.0047590"
    },
    {
      "symbol": "TAGUSDT",
      "date": "2026-07-09",
      "pct": 74.16918429003019,
      "open": "0.00066200",
      "high": "0.0011530",
      "close": "0.00085100"
    },
    {
      "symbol": "TAGUSDT",
      "date": "2026-07-10",
      "pct": 33.1764705882353,
      "open": "0.00085000",
      "high": "0.0011320",
      "close": "0.00097400"
    },
    {
      "symbol": "ESPORTSUSDT",
      "date": "2026-07-09",
      "pct": 41.01297096973441,
      "open": "0.016190",
      "high": "0.022830",
      "close": "0.021430"
    },
    {
      "symbol": "XPINUSDT",
      "date": "2026-07-10",
      "pct": 27.364185110663996,
      "open": "0.0014910",
      "high": "0.0018990",
      "close": "0.0018850"
    },
    {
      "symbol": "EVAAUSDT",
      "date": "2026-07-10",
      "pct": 30.37498319967743,
      "open": "2.2321",
      "high": "2.9101",
      "close": "2.4520"
    },
    {
      "symbol": "CLOUSDT",
      "date": "2026-07-11",
      "pct": 33.046370573273336,
      "open": "0.20444",
      "high": "0.27200",
      "close": "0.25986"
    },
    {
      "symbol": "MMTUSDT",
      "date": "2026-07-10",
      "pct": 37.761780104712045,
      "open": "0.15280",
      "high": "0.21050",
      "close": "0.20310"
    },
    {
      "symbol": "SENTUSDT",
      "date": "2026-07-09",
      "pct": 36.06437454279443,
      "open": "0.013670",
      "high": "0.018600",
      "close": "0.017050"
    },
    {
      "symbol": "USUSDT",
      "date": "2026-07-09",
      "pct": 70.85255424568595,
      "open": "0.017559",
      "high": "0.030000",
      "close": "0.027276"
    },
    {
      "symbol": "KATUSDT",
      "date": "2026-07-10",
      "pct": 26.464646464646453,
      "open": "0.0049500",
      "high": "0.0062600",
      "close": "0.0055360"
    },
    {
      "symbol": "EDGEUSDT",
      "date": "2026-07-09",
      "pct": 26.366322008862625,
      "open": "0.40620",
      "high": "0.51330",
      "close": "0.44250"
    },
    {
      "symbol": "BASEDUSDT",
      "date": "2026-07-09",
      "pct": 30.154905335628225,
      "open": "0.087150",
      "high": "0.11343",
      "close": "0.11148"
    },
    {
      "symbol": "VANRYUSDT",
      "date": "2026-07-12",
      "pct": 26.99256110520723,
      "open": "0.0056460",
      "high": "0.0071700",
      "close": "0.0068260"
    },
    {
      "symbol": "TUSDT",
      "date": "2026-07-12",
      "pct": 28.137128072445034,
      "open": "0.0046380",
      "high": "0.0059430",
      "close": "0.0058740"
    },
    {
      "symbol": "DEXEUSDT",
      "date": "2026-07-12",
      "pct": 30.726987447698743,
      "open": "38.2400",
      "high": "49.9900",
      "close": "46.4300"
    },
    {
      "symbol": "VELVETUSDT",
      "date": "2026-07-12",
      "pct": 29.367606915377614,
      "open": "0.43960",
      "high": "0.56870",
      "close": "0.55910"
    },
    {
      "symbol": "AGLDUSDT",
      "date": "2026-07-12",
      "pct": 30.941408821593143,
      "open": "0.15190",
      "high": "0.19890",
      "close": "0.18820"
    },
    {
      "symbol": "MAGMAUSDT",
      "date": "2026-07-12",
      "pct": 26.555286315520977,
      "open": "0.39205",
      "high": "0.49616",
      "close": "0.49525"
    },
    {
      "symbol": "BILLUSDT",
      "date": "2026-07-12",
      "pct": 28.703929704661945,
      "open": "0.040970",
      "high": "0.052730",
      "close": "0.049590"
    },
    {
      "symbol": "DODOXUSDT",
      "date": "2026-07-12",
      "pct": 53.10632470119523,
      "open": "0.016064",
      "high": "0.024595",
      "close": "0.023257"
    },
    {
      "symbol": "1000XECUSDT",
      "date": "2026-07-13",
      "pct": 43.953211736716895,
      "open": "0.0050440",
      "high": "0.0072610",
      "close": "0.0070170"
    },
    {
      "symbol": "VELVETUSDT",
      "date": "2026-07-13",
      "pct": 31.44446733978982,
      "open": "0.48530",
      "high": "0.63790",
      "close": "0.60180"
    },
    {
      "symbol": "ALLOUSDT",
      "date": "2026-07-13",
      "pct": 42.82805005493181,
      "open": "0.37319",
      "high": "0.53302",
      "close": "0.47273"
    },
    {
      "symbol": "LABUSDT",
      "date": "2026-07-14",
      "pct": 62.84927194018104,
      "open": "0.25410",
      "high": "0.41380",
      "close": "0.40790"
    },
    {
      "symbol": "TRIAUSDT",
      "date": "2026-07-14",
      "pct": 32.592592592592595,
      "open": "0.0081000",
      "high": "0.010740",
      "close": "0.010480"
    },
    {
      "symbol": "SXTUSDT",
      "date": "2026-07-14",
      "pct": 30.514138817480724,
      "open": "0.0077800",
      "high": "0.010154",
      "close": "0.010149"
    },
    {
      "symbol": "MUSDT",
      "date": "2026-07-14",
      "pct": 31.72078457227625,
      "open": "1.2134",
      "high": "1.5983",
      "close": "1.5476"
    },
    {
      "symbol": "EVAAUSDT",
      "date": "2026-07-14",
      "pct": 32.63806589239156,
      "open": "0.84380",
      "high": "1.1192",
      "close": "1.0875"
    },
    {
      "symbol": "GWEIUSDT",
      "date": "2026-07-14",
      "pct": 31.325301204819283,
      "open": "0.049800",
      "high": "0.065400",
      "close": "0.051100"
    },
    {
      "symbol": "SYNUSDT",
      "date": "2026-07-14",
      "pct": 30.623973727421987,
      "open": "0.24360",
      "high": "0.31820",
      "close": "0.27000"
    },
    {
      "symbol": "BSBUSDT",
      "date": "2026-07-14",
      "pct": 41.14434548815325,
      "open": "0.11902",
      "high": "0.16799",
      "close": "0.16156"
    },
    {
      "symbol": "AKEUSDT",
      "date": "2026-07-15",
      "pct": 48.15595363540569,
      "open": "0.00018980",
      "high": "0.00028120",
      "close": "0.00025950"
    },
    {
      "symbol": "USUSDT",
      "date": "2026-07-15",
      "pct": 29.567245400362808,
      "open": "0.027013",
      "high": "0.035000",
      "close": "0.033381"
    },
    {
      "symbol": "SPORTFUNUSDT",
      "date": "2026-07-15",
      "pct": 37.698209718670064,
      "open": "0.019550",
      "high": "0.026920",
      "close": "0.022220"
    },
    {
      "symbol": "PTBUSDT",
      "date": "2026-07-15",
      "pct": 27.97202797202798,
      "open": "0.00050050",
      "high": "0.00064050",
      "close": "0.00056710"
    },
    {
      "symbol": "FLOCKUSDT",
      "date": "2026-07-15",
      "pct": 26.088328075709775,
      "open": "0.031700",
      "high": "0.039970",
      "close": "0.038930"
    },
    {
      "symbol": "DODOXUSDT",
      "date": "2026-07-15",
      "pct": 25.044977197606805,
      "open": "0.023901",
      "high": "0.029887",
      "close": "0.028704"
    },
    {
      "symbol": "SKLUSDT",
      "date": "2026-07-15",
      "pct": 30.85132787292133,
      "open": "0.0040290",
      "high": "0.0052720",
      "close": "0.0046420"
    },
    {
      "symbol": "HOMEUSDT",
      "date": "2026-07-15",
      "pct": 32.168850072780195,
      "open": "0.013740",
      "high": "0.018160",
      "close": "0.018030"
    },
    {
      "symbol": "1000XECUSDT",
      "date": "2026-07-17",
      "pct": 34.72443453329087,
      "open": "0.0062780",
      "high": "0.0084580",
      "close": "0.0076970"
    },
    {
      "symbol": "BANKUSDT",
      "date": "2026-07-16",
      "pct": 26.422843731664386,
      "open": "0.051130",
      "high": "0.064640",
      "close": "0.061210"
    },
    {
      "symbol": "BANKUSDT",
      "date": "2026-07-17",
      "pct": 44.42084626694985,
      "open": "0.061210",
      "high": "0.088400",
      "close": "0.068080"
    },
    {
      "symbol": "TACUSDT",
      "date": "2026-07-16",
      "pct": 28.338983050847453,
      "open": "0.0029500",
      "high": "0.0037860",
      "close": "0.0036590"
    },
    {
      "symbol": "ESPORTSUSDT",
      "date": "2026-07-16",
      "pct": 92.33311302048911,
      "open": "0.015130",
      "high": "0.029100",
      "close": "0.022630"
    },
    {
      "symbol": "AKEUSDT",
      "date": "2026-07-16",
      "pct": 74.04129793510326,
      "open": "0.00067800",
      "high": "0.0011800",
      "close": "0.0010236"
    },
    {
      "symbol": "AKEUSDT",
      "date": "2026-07-17",
      "pct": 36.21178079515484,
      "open": "0.0010237",
      "high": "0.0013944",
      "close": "0.0012296"
    },
    {
      "symbol": "USUSDT",
      "date": "2026-07-16",
      "pct": 34.90654073466618,
      "open": "0.035363",
      "high": "0.047707",
      "close": "0.042800"
    },
    {
      "symbol": "MANTRAUSDT",
      "date": "2026-07-16",
      "pct": 32.08255159474673,
      "open": "0.0063960",
      "high": "0.0084480",
      "close": "0.0069440"
    },
    {
      "symbol": "STARUSDT",
      "date": "2026-07-17",
      "pct": 33.34089877439854,
      "open": "0.17624",
      "high": "0.23500",
      "close": "0.19096"
    },
    {
      "symbol": "OUSDT",
      "date": "2026-07-17",
      "pct": 25.243832472748135,
      "open": "0.52290",
      "high": "0.65490",
      "close": "0.58550"
    },
    {
      "symbol": "SYNUSDT",
      "date": "2026-07-18",
      "pct": 37.67045454545455,
      "open": "0.17600",
      "high": "0.24230",
      "close": "0.21210"
    },
    {
      "symbol": "AVAAIUSDT",
      "date": "2026-07-17",
      "pct": 26.757812499999993,
      "open": "0.0061440",
      "high": "0.0077880",
      "close": "0.0075970"
    },
    {
      "symbol": "ESPORTSUSDT",
      "date": "2026-07-17",
      "pct": 42.825607064017646,
      "open": "0.022650",
      "high": "0.032350",
      "close": "0.031050"
    },
    {
      "symbol": "TOSHIUSDT",
      "date": "2026-07-18",
      "pct": 29.674418604651166,
      "open": "0.00010750",
      "high": "0.00013940",
      "close": "0.00012620"
    },
    {
      "symbol": "AKEUSDT",
      "date": "2026-07-18",
      "pct": 25.58995002776236,
      "open": "0.0014408",
      "high": "0.0018095",
      "close": "0.0017569"
    },
    {
      "symbol": "TRADOORUSDT",
      "date": "2026-07-18",
      "pct": 25.803551359856137,
      "open": "0.44490",
      "high": "0.55970",
      "close": "0.51920"
    },
    {
      "symbol": "AVAAIUSDT",
      "date": "2026-07-18",
      "pct": 25.661968120142287,
      "open": "0.0075910",
      "high": "0.0095390",
      "close": "0.0093780"
    },
    {
      "symbol": "BUSDT",
      "date": "2026-07-18",
      "pct": 27.09059233449478,
      "open": "0.11480",
      "high": "0.14590",
      "close": "0.13980"
    },
    {
      "symbol": "1000XECUSDT",
      "date": "2026-07-18",
      "pct": 27.038208809929426,
      "open": "0.0082180",
      "high": "0.010440",
      "close": "0.0087210"
    },
    {
      "symbol": "TLMUSDT",
      "date": "2026-07-18",
      "pct": 28.437724982001434,
      "open": "0.0013890",
      "high": "0.0017840",
      "close": "0.0017310"
    },
    {
      "symbol": "BANKUSDT",
      "date": "2026-07-18",
      "pct": 73.49978720385873,
      "open": "0.070490",
      "high": "0.12230",
      "close": "0.11112"
    },
    {
      "symbol": "BULLAUSDT",
      "date": "2026-07-19",
      "pct": 25.520399666944204,
      "open": "0.0096080",
      "high": "0.012060",
      "close": "0.011836"
    },
    {
      "symbol": "ESPORTSUSDT",
      "date": "2026-07-19",
      "pct": 59.92102665350443,
      "open": "0.030390",
      "high": "0.048600",
      "close": "0.041790"
    },
    {
      "symbol": "LYNUSDT",
      "date": "2026-07-18",
      "pct": 25.21886472747812,
      "open": "0.035410",
      "high": "0.044340",
      "close": "0.037140"
    },
    {
      "symbol": "TLMUSDT",
      "date": "2026-07-19",
      "pct": 42.46100519930676,
      "open": "0.0017310",
      "high": "0.0024660",
      "close": "0.0023260"
    },
    {
      "symbol": "GUSDT",
      "date": "2026-07-19",
      "pct": 42.450058754406584,
      "open": "0.0034040",
      "high": "0.0048490",
      "close": "0.0036120"
    },
    {
      "symbol": "SOLVUSDT",
      "date": "2026-07-19",
      "pct": 29.68445656408259,
      "open": "0.0025670",
      "high": "0.0033290",
      "close": "0.0030310"
    },
    {
      "symbol": "BANKUSDT",
      "date": "2026-07-19",
      "pct": 74.4330453563715,
      "open": "0.11112",
      "high": "0.19383",
      "close": "0.18129"
    },
    {
      "symbol": "BUSDT",
      "date": "2026-07-19",
      "pct": 35.568862275449085,
      "open": "0.16700",
      "high": "0.22640",
      "close": "0.19350"
    },
    {
      "symbol": "TAGUSDT",
      "date": "2026-07-19",
      "pct": 25.024533856722282,
      "open": "0.0010190",
      "high": "0.0012740",
      "close": "0.0012000"
    }
  ],
  "_meta": {
    "lastUpdate": "2026-07-19T14:55:21.635Z",
    "threshold": 25,
    "lookbackDays": 4
  }
}